{
  "Q7378029": [
    {
      "id": "Q3401756",
      "label": "Premier of the Turks and Caicos Islands",
      "title": "Premier of the Turks and Caicos Islands",
      "description": "political leader and head of government",
      "qualifiers": {
        "P580": "2012-11-13",
        "P1365": "Galmo Williams"
      }
    }
  ],
  "Q7489886": [
    {
      "id": "Q2285706",
      "label": "head of government",
      "title": "head of government",
      "description": "chief officer of the executive branch of a government"
    }
  ],
  "Q4700892": [
    {
      "id": "Q4018482",
      "label": "education minister",
      "title": "education minister",
      "description": "minister in charge of education matters"
    }
  ]
}