{
  "Q20987557": {
    "identifiers": [
      {
        "scheme": "wikidata",
        "identifier": "Q20987557"
      }
    ],
    "other_names": [
      {
        "lang": "en",
        "name": "Moldovan parliamentary election, 2019",
        "note": "multilingual",
        "source": "wikidata-label"
      },
      {
        "lang": "ro",
        "name": "Rezultatele sondajelor de opinie pentru următoarele alegeri parlamentare din Republica Moldova",
        "note": "multilingual",
        "source": "wikidata-label"
      },
      {
        "lang": "zh",
        "name": "2018年摩爾多瓦國會選舉",
        "note": "multilingual",
        "source": "wikidata-label"
      },
      {
        "lang": "de",
        "name": "Parlamentswahl in Moldawien 2019",
        "note": "multilingual",
        "source": "wikidata-label"
      },
      {
        "lang": "ru",
        "name": "Парламентские выборы в Молдавии (2018)",
        "note": "multilingual",
        "source": "wikidata-label"
      },
      {
        "lang": "fa",
        "name": "انتخابات پارلمانی مولداوی",
        "note": "multilingual",
        "source": "wikidata-label"
      },
      {
        "lang": "fr",
        "name": "Élections législatives moldaves de 2018",
        "note": "multilingual",
        "source": "wikidata-label"
      },
      {
        "lang": "es",
        "name": "Elecciones parlamentarias de Moldavia de 2019",
        "note": "multilingual",
        "source": "wikidata-label"
      },
      {
        "lang": "ast",
        "name": "eleiciones parllamentaries de Moldavia de 2019",
        "note": "multilingual",
        "source": "wikidata-label"
      },
      {
        "lang": "cs",
        "name": "Parlamentní volby v Moldavsku 2019",
        "note": "multilingual",
        "source": "wikidata-label"
      },
      {
        "lang": "ja",
        "name": "2019年モルドバ総選挙",
        "note": "multilingual",
        "source": "wikidata-label"
      },
      {
        "lang": "zh",
        "name": "2019年摩爾多瓦國會選舉",
        "note": "multilingual",
        "source": "wikidata-alias"
      }
    ],
    "dates": [
      "2019-02-24"
    ],
    "follows": "Moldovan parliamentary election, 2014",
    "office": "member of the Parliament of Moldova"
  }
}